[{
    
    "id":1,
    "name":"Story Book",
    
    "title":"Lorem, ipsum dolor sit amet consectetur adip",
    "price":0,
    
    
    
    "category":"Free",
    
    
    
    "image":""
    
    
    
    

},
{
    
    "id":2,
    "name":"Story Book1",
    
    "title":"Lorem, ipsum dolor sit amet consectetur adip",
    "price":20,
    
    
    
    "category":"story",
    
    
    
    "image":""
    
    
    
    

},
{
    
    "id":3,
    "name":"Story Book2",
    
    "title":"Lorem, ipsum dolor sit amet consectetur adip",
    "price":50,
    
    
    
    "category":"cooking",
    
    
    
    "image":""
    
    
    
    

},
{
    
    "id":4,
    "name":"Story Book3",
    
    "title":"Lorem, ipsum dolor sit amet consectetur adip",
    "price":0,
    
    
    
    "category":"Free",
    
    
    
    "image":""
    
    
    
    

},
{
    
    "id":5,
    "name":"Story Book4",
    
    "title":"Lorem, ipsum dolor sit amet consectetur adip",
    "price":0,
    
    
    
    "category":"Free",
    
    
    
    "image":""
    
    
    
    

},
{
    
    "id":6,
    "name":"Story Book",
    
    "title":"Lorem, ipsum dolor sit amet consectetur adip",
    "price":0,
    
    
    
    "category":"Free",
    
    
    
    "image":""
    
    
    
    

},
{
    
    "id":7,
    "name":"Story Book",
    
    "title":"Lorem, ipsum dolor sit amet consectetur adip",
    "price":0,
    
    
    
    "category":"Free",
    
    
    
    "image":""
    
    
    
    

},
{
    
    "id":8,
    "name":"Story Book",
    
    "title":"Lorem, ipsum dolor sit amet consectetur adip",
    "price":0,
    
    
    
    "category":"Free",
    
    
    
    "image":""
    
    
    
    

},
{
    
    "id":9,
    "name":"Story Book",
    
    "title":"Lorem, ipsum dolor sit amet consectetur adip",
    "price":100,
    
    
    
    "category":"education",
    
    
    
    "image":""
    
    
    
    

},
{
    
    "id":10,
    "name":"Story Book",
    
    "title":"Lorem, ipsum dolor sit amet consectetur adip",
    "price":40,
    
    
    
    "category":"entertainment",
    
    
    
    "image":""
    
    
    
    

}
]

    